{
  "animais": {
    "mamiferos": {
      "carnívoros": {
        "felinos": ["Leões", "Tigres", "Jaguars", "Leopardos"]
      },
      "herbívoros": {
        "equídeos": ["Cavalos", "Zebras", "Asnos"],
        "bovídeos": ["Bois", "Búfalos", "Antílopes", "Cabras"]
      },
      "primatas": ["Gorilas", "Chimpanzés", "Orangotango"]
    },
    "aves": {
      "rapinas": ["aguia", "falcao", "coruja"],
      "passeriformes": ["pardal", "canario", "sabiá"],
      "natatoriais": ["pato", "cisne", "pinguim"]
    }
  }
}
